LICENSE
MANIFEST.in
README.rst
setup.py
google/__init__.py
google/cloud/__init__.py
google/cloud/proto/__init__.py
google/cloud/proto/speech/__init__.py
google/cloud/proto/speech/v1beta1/__init__.py
google/cloud/proto/speech/v1beta1/cloud_speech_pb2.py
google/cloud/proto/speech/v1beta1/cloud_speech_pb2_grpc.py
proto_google_cloud_speech_v1beta1.egg-info/PKG-INFO
proto_google_cloud_speech_v1beta1.egg-info/SOURCES.txt
proto_google_cloud_speech_v1beta1.egg-info/dependency_links.txt
proto_google_cloud_speech_v1beta1.egg-info/namespace_packages.txt
proto_google_cloud_speech_v1beta1.egg-info/requires.txt
proto_google_cloud_speech_v1beta1.egg-info/top_level.txt